{
  "general": {
    "timezone": "Europe/Berlin"
  },
  "sections": [
    {
      "id": "01_generalInformation",
      "type": "fieldSection",
      "config": {
        "headline": {
          "text": {
            "de": "Allgemeine Informationen",
            "en": "General Information"
          },
          "pdfHide": true
        }
      },
      "fields": [
        {
          "id": "pdfHeadline1",
          "type": "headlineDisplay",
          "config": {
            "text": {
              "de": "Allgemeine Informationen",
              "en": "General Information"
            },
            "pdfTextSize": "H2",
            "uiHide": true
          }
        },
        {
          "id": "customer",
          "type": "companySingleSelect",
          "config": {
            "label": {
              "text": {
                "de": "Anlagenstandort/Kunde",
                "en": "Asset Location/Customer"
              }
            },
            "required": true,
            "pdfWidth": 0.5,
            "useAsFilterForFields": [
              "asset"
            ],
            "prefill": {
              "selectedCompany": [
                {
                  "input": "organizationId",
                  "steps": []
                }
              ]
            }
          }
        },
        {
          "id": "contactPerson",
          "type": "singleLineTextInput",
          "config": {
            "label": {
              "text": {
                "de": "Ansprechperson",
                "en": "Contact Person"
              }
            },
            "pdfWidth": 0.5
          }
        },
        {
          "id": "assetAddress",
          "type": "addressInput",
          "config": {
            "label": {
              "text": {
                "de": "Anschrift",
                "en": "Address"
              }
            },
            "pdfWidth": 0.5,
            "prefill": {
              "value": [
                {
                  "input": "workOrderId",
                  "steps": [
                    "workOrderIdToWorkOrder",
                    "workOrderToLocationAddress"
                  ]
                }
              ]
            },
            "onChange": [
              {
                "target": {
                  "id": "10_signatureTechnician",
                  "propertyName": "location"
                },
                "steps": [
                  "addressToCityString"
                ]
              }
            ]
          }
        },
        {
          "id": "telephoneCustomer",
          "type": "phoneNumberInput",
          "config": {
            "label": {
              "text": {
                "de": "Telefon / Telefax / Funk",
                "en": "Telephone / Fax"
              }
            },
            "pdfWidth": 0.5
          }
        }
      ]
    },
    {
      "id": "02_machineData",
      "type": "fieldSection",
      "config": {
        "headline": {
          "text": {
            "de": "1. Maschinendaten",
            "en": "1. Machine Data"
          },
          "pdfHide": true
        }
      },
      "fields": [
        {
          "id": "whitespace1",
          "type": "headlineDisplay",
          "config": {
            "text": {
              "de": "",
              "en": ""
            },
            "uiHide": true,
            "pdfTextSize": "H2"
          }
        },
        {
          "id": "line1",
          "type": "htmlDisplay",
          "config": {
            "text": {
              "de": "<hr>",
              "en": "<hr>"
            },
            "uiHide": true
          }
        },
        {
          "id": "pdfHeadline2",
          "type": "headlineDisplay",
          "config": {
            "text": {
              "de": "1. Maschinendaten",
              "en": "1. Machine Data"
            },
            "pdfTextSize": "H2",
            "uiHide": true
          }
        },
        {
          "id": "asset",
          "type": "assetMultiSelect",
          "config": {
            "disabled": false,
            "pdfHide": false,
            "pdfHideIfValueIsEmpty": false,
            "pdfWidth": 1,
            "requiredAmountOfEntries": 1,
            "label": {
              "text": {
                "en": "Roots Blower",
                "de": "Drehkolbengebläse"
              }
            },
            "value": {
              "disableAssetFormInstanceRelationship": false,
              "disableCreation": false,
              "pdfHide": false,
              "pdfStartInNewLine": false,
              "pdfAddLineBreaks": false
            }
          }
        },
        {
          "id": "productionYear",
          "type": "singleLineTextInput",
          "config": {
            "label": {
              "text": {
                "de": "Baujahr",
                "en": "Year of Production"
              }
            },
            "pdfWidth": 0.5
          }
        },
        {
          "id": "outletPressure",
          "type": "singleLineTextInput",
          "config": {
            "label": {
              "text": {
                "de": "Austrittsdruck (bar)",
                "en": "Outlet Pressure (bar)"
              }
            },
            "pdfWidth": 0.5
          }
        },
        {
          "id": "roomTemperature",
          "type": "singleLineTextInput",
          "config": {
            "label": {
              "text": {
                "de": "Raumtemperatur (°C)",
                "en": "Room Temperature (°C)"
              }
            },
            "pdfWidth": 0.5
          }
        },
        {
          "id": "power",
          "type": "singleLineTextInput",
          "config": {
            "label": {
              "text": {
                "de": "Motorleistung",
                "en": "Engine Power"
              }
            },
            "pdfWidth": 0.5
          }
        },
        {
          "id": "operatingHours",
          "type": "singleLineTextInput",
          "config": {
            "label": {
              "text": {
                "de": "Anzahl Betriebsstunden (alt/neu)",
                "en": "Number of operating hours (old/new)"
              }
            },
            "pdfWidth": 0.5
          }
        },
        {
          "id": "oilType",
          "type": "singleLineTextInput",
          "config": {
            "label": {
              "text": {
                "de": "Verwendete Ölsorte",
                "en": "Used Oil Type"
              }
            },
            "pdfWidth": 0.5
          }
        },
        {
          "id": "oilChange",
          "type": "staticSingleSelect",
          "config": {
            "label": {
              "text": {
                "de": "Ölwechsel",
                "en": "Oil Change"
              }
            },
            "value": {
              "options": {
                "yes": {
                  "de": "Ja",
                  "en": "Yes"
                },
                "no": {
                  "de": "Nein",
                  "en": "No"
                }
              }
            },
            "pdfWidth": 0.5
          }
        }
      ]
    },
    {
      "id": "03_additionalComponents",
      "type": "fieldSection",
      "config": {
        "headline": {
          "text": {
            "de": "2. Zusatzkomponenten des Drehkolbengebläses",
            "en": "2. Additional Components of Roots Blower"
          },
          "pdfHide": true
        }
      },
      "fields": [
        {
          "id": "whitespace2",
          "type": "headlineDisplay",
          "config": {
            "text": {
              "de": "",
              "en": ""
            },
            "uiHide": true,
            "pdfTextSize": "H2"
          }
        },
        {
          "id": "line2",
          "type": "htmlDisplay",
          "config": {
            "text": {
              "de": "<hr>",
              "en": "<hr>"
            },
            "uiHide": true
          }
        },
        {
          "id": "pdfHeadline3",
          "type": "headlineDisplay",
          "config": {
            "text": {
              "de": "2. Zusatzkomponenten des Drehkolbengebläses",
              "en": "2. Additional Components of Roots Blower"
            },
            "pdfTextSize": "H2",
            "uiHide": true
          }
        },
        {
          "id": "schallhaube",
          "type": "staticSingleSelect",
          "config": {
            "label": {
              "text": {
                "de": "Schallhaube",
                "en": "Sound Hood"
              }
            },
            "value": {
              "options": {
                "yes": {
                  "de": "Ja",
                  "en": "Yes"
                },
                "no": {
                  "de": "Nein",
                  "en": "No"
                }
              }
            },
            "pdfWidth": 0.5
          }
        },
        {
          "id": "fremdbelüftungDerHaube",
          "type": "staticSingleSelect",
          "config": {
            "label": {
              "text": {
                "de": "Fremdbelüftung der Haube",
                "en": "Forced ventilation of the hood"
              }
            },
            "value": {
              "options": {
                "yes": {
                  "de": "Ja",
                  "en": "Yes"
                },
                "no": {
                  "de": "Nein",
                  "en": "No"
                }
              }
            },
            "pdfWidth": 0.5
          }
        },
        {
          "id": "raumbelüftung",
          "type": "staticSingleSelect",
          "config": {
            "label": {
              "text": {
                "de": "Raumbelüftung",
                "en": "Room Ventilation"
              }
            },
            "value": {
              "options": {
                "yes": {
                  "de": "Ja",
                  "en": "Yes"
                },
                "no": {
                  "de": "Nein",
                  "en": "No"
                }
              }
            },
            "pdfWidth": 0.5
          }
        }
      ]
    },
    {
      "id": "04_inspectionOfRootsBlower",
      "type": "fieldSection",
      "config": {
        "headline": {
          "text": {
            "de": "3. Inspektion des Drehkolbengebläses",
            "en": "3. Inspection of Roots Blower"
          },
          "pdfHide": true
        }
      },
      "fields": [
        {
          "id": "whitespace3",
          "type": "headlineDisplay",
          "config": {
            "text": {
              "de": "",
              "en": ""
            },
            "uiHide": true,
            "pdfTextSize": "H2"
          }
        },
        {
          "id": "line3",
          "type": "htmlDisplay",
          "config": {
            "text": {
              "de": "<hr>",
              "en": "<hr>"
            },
            "uiHide": true
          }
        },
        {
          "id": "pdfHeadline4",
          "type": "headlineDisplay",
          "config": {
            "text": {
              "de": "3. Inspektion des Drehkolbengebläses",
              "en": "3. Inspection of Roots Blower"
            },
            "pdfTextSize": "H2",
            "uiHide": true
          }
        },
        {
          "id": "headlineSmoothness",
          "type": "headlineDisplay",
          "config": {
            "text": {
              "de": "3.1 Laufruhe des Gebläses",
              "en": "3.1 Smoothness of Blower"
            },
            "type": "H3"
          }
        },
        {
          "id": "smoothness",
          "type": "staticSingleSelect",
          "config": {
            "label": {
              "text": {
                "de": "Laufruhe",
                "en": "Smoothness"
              }
            },
            "value": {
              "options": {
                "good": {
                  "de": "Gut",
                  "en": "Good"
                },
                "bad": {
                  "de": "Schlecht",
                  "en": "Bad"
                }
              }
            },
            "pdfWidth": 0.5
          }
        },
        {
          "id": "causeSmoothness4",
          "type": "singleLineTextInput",
          "config": {
            "label": {
              "text": {
                "de": "wenn schlecht, evtl. Ursache",
                "en": "in case of bad smoothness, give cause"
              }
            },
            "pdfWidth": 0.5,
            "pdfHideIfValueIsEmpty": true
          }
        },
        {
          "id": "line4",
          "type": "htmlDisplay",
          "config": {
            "text": {
              "de": "<hr>",
              "en": "<hr>"
            },
            "uiHide": true
          }
        },
        {
          "id": "headlineOilLevel",
          "type": "headlineDisplay",
          "config": {
            "text": {
              "de": "3.2 Ölstand des Gebläses",
              "en": "3.2 Oil Level of Blower"
            },
            "type": "H3"
          }
        },
        {
          "id": "helpTextOilLevel",
          "type": "htmlDisplay",
          "config": {
            "text": {
              "de": "Die erford. Ölstandhöhe ist Mitte Schauglas",
              "en": "The required oil level is in the middle of the sight glass"
            },
            "pdfHide": true
          }
        },
        {
          "id": "oilLevel",
          "type": "staticSingleSelect",
          "config": {
            "label": {
              "text": {
                "de": "Ölstand vor der Wartung",
                "en": "Oil level before maintenance"
              }
            },
            "value": {
              "options": {
                "good": {
                  "de": "Gut",
                  "en": "Good"
                },
                "tooLow": {
                  "de": "zu niedrig",
                  "en": "too low"
                },
                "tooHigh": {
                  "de": "zu hoch",
                  "en": "too high"
                }
              }
            }
          }
        },
        {
          "id": "line5",
          "type": "htmlDisplay",
          "config": {
            "text": {
              "de": "<hr>",
              "en": "<hr>"
            },
            "uiHide": true
          }
        },
        {
          "id": "headlineoilTightness",
          "type": "headlineDisplay",
          "config": {
            "text": {
              "de": "3.3 Öldichtigkeit des Gebläses",
              "en": "3.3 Oil Tightness of Blower"
            },
            "type": "H3"
          }
        },
        {
          "id": "helpTextOilTightness",
          "type": "htmlDisplay",
          "config": {
            "text": {
              "de": "Das Gebläse muss ölfrei sein, d.h es dürfen keine Ölundichtigkeiten festgestellt werden.",
              "en": "The blower must be oil-free, i.e. no oil leaks may be found."
            },
            "pdfHide": true
          }
        },
        {
          "id": "oilTightness",
          "type": "staticSingleSelect",
          "config": {
            "label": {
              "text": {
                "de": "Dichtigkeit",
                "en": "Tightness"
              }
            },
            "value": {
              "options": {
                "yes": {
                  "de": "Ja",
                  "en": "Yes"
                },
                "no": {
                  "de": "Nein",
                  "en": "No"
                }
              }
            },
            "pdfWidth": 0.5
          }
        },
        {
          "id": "positionOfOilLeak",
          "type": "singleLineTextInput",
          "config": {
            "label": {
              "text": {
                "de": "wenn nein, Stelle der Ölundichtigkeit",
                "en": "in case of leakage, give position of leakage"
              }
            },
            "pdfWidth": 0.5,
            "pdfHideIfValueIsEmpty": true
          }
        },
        {
          "id": "causeOfOilLeak",
          "type": "multiLineTextInput",
          "config": {
            "label": {
              "text": {
                "de": "evtl. Ursache",
                "en": "in case of leakage, give cause of leakage"
              }
            },
            "pdfWidth": 0.5,
            "pdfHideIfValueIsEmpty": true
          }
        },
        {
          "id": "extendOfOilLeak",
          "type": "multiLineTextInput",
          "config": {
            "label": {
              "text": {
                "de": "Undichtigkeitsgrad",
                "en": "Extend of leakage"
              }
            },
            "pdfWidth": 0.5
          }
        },
        {
          "id": "line6",
          "type": "htmlDisplay",
          "config": {
            "text": {
              "de": "<hr>",
              "en": "<hr>"
            },
            "uiHide": true
          }
        },
        {
          "id": "headlineSuctionFilter",
          "type": "headlineDisplay",
          "config": {
            "text": {
              "de": "3.4 Inspektion der Ansaugfilter",
              "en": "3.4 Inspection of Suction Filter"
            },
            "type": "H3"
          }
        },
        {
          "id": "helpTextSuctionFilter",
          "type": "htmlDisplay",
          "config": {
            "text": {
              "de": "Damit das Gebläse vor unzulässig hoher Druckdifferenz geschützt werden kann, muss der Ansaugfilter in regelmäßigen Zeitintervallen gereinigt werden.",
              "en": "In order to protect the blower against impermissibly high pressure difference, the intake filter must be cleaned at regular time intervals."
            },
            "pdfHide": true
          }
        },
        {
          "id": "suctionFilter",
          "type": "staticSingleSelect",
          "config": {
            "label": {
              "text": {
                "de": "Ansaugfilter",
                "en": "Suction Filter"
              }
            },
            "value": {
              "options": {
                "1": {
                  "de": "Sauber",
                  "en": "Clean"
                },
                "2": {
                  "de": "Verschmutzt",
                  "en": "Dirty"
                }
              }
            },
            "pdfWidth": 0.5
          }
        },
        {
          "id": "suctionFilterBlocked",
          "type": "staticSingleSelect",
          "config": {
            "label": {
              "text": {
                "de": "Ansaugfilter ist zu",
                "en": "Suction Filter is blocked"
              }
            },
            "value": {
              "options": {
                "1": {
                  "de": "Erneuern",
                  "en": "Renew"
                },
                "2": {
                  "de": "Reinigen",
                  "en": "Clean"
                }
              }
            },
            "pdfWidth": 0.5
          }
        },
        {
          "id": "line7",
          "type": "htmlDisplay",
          "config": {
            "text": {
              "de": "<hr>",
              "en": "<hr>"
            },
            "uiHide": true
          }
        },
        {
          "id": "headlineConveyorRoom",
          "type": "headlineDisplay",
          "config": {
            "text": {
              "de": "3.5 Inspektion des Förderraumes (falls erforderlich)",
              "en": "3.5 Inspection of the conveyor space (if necessary)"
            },
            "type": "H3"
          }
        },
        {
          "id": "helpTextConveyorRoom",
          "type": "htmlDisplay",
          "config": {
            "text": {
              "de": "Der Förderraum ist nach Entfernen des Ansaugfilters (KIII + KS Aggregat) zu kontrollieren auf:",
              "en": "The conveyor space should be checked for the following after removing the intake filter (KIII + KS unit):"
            },
            "pdfHide": true
          }
        },
        {
          "id": "pollution",
          "type": "staticSingleSelect",
          "config": {
            "label": {
              "text": {
                "de": "Verschmutzung",
                "en": "Pollution"
              }
            },
            "value": {
              "options": {
                "yes": {
                  "de": "Sauber",
                  "en": "Clean"
                },
                "no": {
                  "de": "Verschmutzt",
                  "en": "Dirty"
                }
              }
            },
            "pdfWidth": 0.5
          }
        },
        {
          "id": "contactPoints",
          "type": "staticSingleSelect",
          "config": {
            "label": {
              "text": {
                "de": "sichtbare Anlaufstellen",
                "en": "visible contact points"
              }
            },
            "value": {
              "options": {
                "yes": {
                  "de": "Ja",
                  "en": "Yes"
                },
                "no": {
                  "de": "Nein",
                  "en": "No"
                }
              }
            },
            "pdfWidth": 0.5
          }
        },
        {
          "id": "locationContactPoints",
          "type": "singleLineTextInput",
          "config": {
            "label": {
              "text": {
                "de": "wenn ja, Lage der Anlaufstellen",
                "en": "in case of visible contact points, give location of contact points"
              }
            },
            "pdfHideIfValueIsEmpty": true
          }
        },
        {
          "id": "line8",
          "type": "htmlDisplay",
          "config": {
            "text": {
              "de": "<hr>",
              "en": "<hr>"
            },
            "uiHide": true
          }
        },
        {
          "id": "headlineIntakeSilencer",
          "type": "headlineDisplay",
          "config": {
            "text": {
              "de": "3.6 Inspektion des Ansaugschalldämpfers (falls erforderlich)",
              "en": "3.6 Inspection of intake silencer (if necessary)"
            },
            "type": "H3"
          }
        },
        {
          "id": "headlineIntakeSilencer2",
          "type": "htmlDisplay",
          "config": {
            "text": {
              "de": "Der Ansaugschalldämpfer wird auf Verschmutzung und durch Abfüllen mit der Hand auf Dichtigkeit geprüft.",
              "en": "The intake silencer is checked for contamination and tightness by hand."
            },
            "pdfHide": true
          }
        },
        {
          "id": "pollutionIntakeSilencer",
          "type": "staticSingleSelect",
          "config": {
            "label": {
              "text": {
                "de": "Ansaugschalldämpfer",
                "en": "Intake Silencer"
              }
            },
            "value": {
              "options": {
                "clean": {
                  "de": "Sauber",
                  "en": "Clean"
                },
                "dirty": {
                  "de": "Verschmutzt",
                  "en": "Dirty"
                }
              }
            },
            "pdfWidth": 0.5
          }
        },
        {
          "id": "tightnessIntakeSilencer",
          "type": "staticSingleSelect",
          "config": {
            "label": {
              "text": {
                "de": "Ansaugschalldämpfer",
                "en": "Intake Silencer"
              }
            },
            "value": {
              "options": {
                "tight": {
                  "de": "Dicht",
                  "en": "Tight"
                },
                "leaky": {
                  "de": "Undicht",
                  "en": "Leaky"
                }
              }
            },
            "pdfWidth": 0.5
          }
        },
        {
          "id": "locationIntakeSilencerLeakage",
          "type": "multiLineTextInput",
          "config": {
            "label": {
              "text": {
                "de": "Stelle der Undichtigkeit",
                "en": "Location of leakage"
              }
            },
            "pdfWidth": 0.5,
            "pdfHideIfValueIsEmpty": true
          }
        },
        {
          "id": "tightnessPressureSilencer",
          "type": "staticSingleSelect",
          "config": {
            "label": {
              "text": {
                "de": "Druckschalldämpfer",
                "en": "Pressure Silencer"
              }
            },
            "value": {
              "options": {
                "tight": {
                  "de": "Dicht",
                  "en": "Tight"
                },
                "leaky": {
                  "de": "Undicht",
                  "en": "Leaky"
                }
              }
            },
            "pdfWidth": 0.5
          }
        },
        {
          "id": "locationPressureSilencerLeakage",
          "type": "multiLineTextInput",
          "config": {
            "label": {
              "text": {
                "de": "Stelle der Undichtigkeit",
                "en": "Location of leakage"
              }
            },
            "pdfWidth": 0.5,
            "pdfHideIfValueIsEmpty": true
          }
        },
        {
          "id": "headlineIntakeSilencer3",
          "type": "htmlDisplay",
          "config": {
            "text": {
              "de": "Beim KS-Aggregat sind bei nachlassender Schalldämpfung die Absorptionsfornteile auszutauschen.",
              "en": "Regarding the KS unit, the absorption parts must be replaced if the sound insulation decreases."
            },
            "pdfHide": true
          }
        },
        {
          "id": "replaceMoldings",
          "type": "staticSingleSelect",
          "config": {
            "label": {
              "text": {
                "de": "Formteile sind auszutauschen",
                "en": "Moldings need replacement"
              }
            },
            "value": {
              "options": {
                "yes": {
                  "de": "Ja",
                  "en": "Yes"
                },
                "no": {
                  "de": "Nein",
                  "en": "No"
                }
              }
            },
            "pdfWidth": 0.5
          }
        },
        {
          "id": "line9",
          "type": "htmlDisplay",
          "config": {
            "text": {
              "de": "<hr>",
              "en": "<hr>"
            },
            "uiHide": true
          }
        },
        {
          "id": "headlineFlyingOperation",
          "type": "headlineDisplay",
          "config": {
            "text": {
              "de": "3.6.1 Fliegender Antrieb",
              "en": "3.6.1 Flying Operation"
            },
            "type": "H3"
          }
        },
        {
          "id": "headlineFlyingOperation2",
          "type": "htmlDisplay",
          "config": {
            "text": {
              "de": "Der Riemenantrieb muss fachgerecht gespannt und ausgerichtet sein.",
              "en": "The belt drive must be professionally tensioned and aligned."
            },
            "pdfHide": true
          }
        },
        {
          "id": "tension",
          "type": "staticSingleSelect",
          "config": {
            "label": {
              "text": {
                "de": "Spannung",
                "en": "Tension"
              }
            },
            "value": {
              "options": {
                "good": {
                  "de": "Gut",
                  "en": "Good"
                },
                "bad": {
                  "de": "Schlecht",
                  "en": "Bad"
                }
              }
            },
            "pdfWidth": 0.5
          }
        },
        {
          "id": "alignment",
          "type": "staticSingleSelect",
          "config": {
            "label": {
              "text": {
                "de": "Ausrichtung",
                "en": "Alignment"
              }
            },
            "value": {
              "options": {
                "good": {
                  "de": "Gut",
                  "en": "Good"
                },
                "bad": {
                  "de": "Schlecht",
                  "en": "Bad"
                }
              }
            },
            "pdfWidth": 0.5
          }
        },
        {
          "id": "smoothness2",
          "type": "staticSingleSelect",
          "config": {
            "label": {
              "text": {
                "de": "Laufruhe",
                "en": "Smoothness"
              }
            },
            "value": {
              "options": {
                "good": {
                  "de": "Gut",
                  "en": "Good"
                },
                "bad": {
                  "de": "Schlecht",
                  "en": "Bad"
                }
              }
            },
            "pdfWidth": 0.5
          }
        },
        {
          "id": "headlineFlyingOperation3",
          "type": "htmlDisplay",
          "config": {
            "text": {
              "de": "Die Keilriemen dürfen keinen Schlupf aufweisen.",
              "en": "The V-belts must not slip."
            },
            "pdfHide": true
          }
        },
        {
          "id": "conditionVBelts",
          "type": "staticSingleSelect",
          "config": {
            "label": {
              "text": {
                "de": "Zustand der Keilriemen",
                "en": "Condition of the V-belts"
              }
            },
            "value": {
              "options": {
                "good": {
                  "de": "Gut",
                  "en": "Good"
                },
                "bad": {
                  "de": "Schlecht",
                  "en": "Bad"
                }
              }
            },
            "pdfWidth": 0.5
          }
        },
        {
          "id": "conditionPulleys",
          "type": "staticSingleSelect",
          "config": {
            "label": {
              "text": {
                "de": "Zustand der Riemenscheiben",
                "en": "Condition of the pulleys"
              }
            },
            "value": {
              "options": {
                "good": {
                  "de": "Gut",
                  "en": "Good"
                },
                "bad": {
                  "de": "Schlecht",
                  "en": "Bad"
                }
              }
            },
            "pdfWidth": 0.5
          }
        },
        {
          "id": "conditionBeltGuard",
          "type": "staticSingleSelect",
          "config": {
            "label": {
              "text": {
                "de": "Zustand des Riemenschutzes",
                "en": "Condition belt guard"
              }
            },
            "value": {
              "options": {
                "good": {
                  "de": "Gut",
                  "en": "Good"
                },
                "bad": {
                  "de": "Schlecht",
                  "en": "Bad"
                }
              }
            },
            "pdfWidth": 0.5
          }
        },
        {
          "id": "line10",
          "type": "htmlDisplay",
          "config": {
            "text": {
              "de": "<hr>",
              "en": "<hr>"
            },
            "uiHide": true
          }
        },
        {
          "id": "headlineSafetyValve",
          "type": "headlineDisplay",
          "config": {
            "text": {
              "de": "3.7 Überprüfung des Sicherheitsventils",
              "en": "3.7 Checking the safety valve"
            },
            "type": "H3"
          }
        },
        {
          "id": "headlineSafetyValve2",
          "type": "htmlDisplay",
          "config": {
            "text": {
              "de": "Das Sicherheitsventil ist kein Regelorgan und darf nicht als solches genutzt werden. Eine Überprüfung erfollgt durch das Anheben des Ventils mittels zwei Schraubenziehern.",
              "en": "The safety valve is not a control device and should not be used as such. It should be checked by lifting the valve using two screwdrivers."
            },
            "pdfHide": true
          }
        },
        {
          "id": "conditionSafetyValve",
          "type": "staticSingleSelect",
          "config": {
            "label": {
              "text": {
                "de": "Funktionstüchtigkeit",
                "en": "Functionality"
              }
            },
            "value": {
              "options": {
                "good": {
                  "de": "Gut",
                  "en": "Good"
                },
                "bad": {
                  "de": "Schlecht",
                  "en": "Bad"
                }
              }
            },
            "pdfWidth": 0.5
          }
        },
        {
          "id": "causeBadFunctionality",
          "type": "multiLineTextInput",
          "config": {
            "label": {
              "text": {
                "de": "wenn schlecht, Ursache",
                "en": "in case of bad functionality, give cause"
              }
            },
            "pdfWidth": 0.5,
            "pdfHideIfValueIsEmpty": true
          }
        },
        {
          "id": "line11",
          "type": "htmlDisplay",
          "config": {
            "text": {
              "de": "<hr>",
              "en": "<hr>"
            },
            "uiHide": true
          }
        },
        {
          "id": "headlineStartRelief",
          "type": "headlineDisplay",
          "config": {
            "text": {
              "de": "3.8 Überprüfung der Anfahrentlastung",
              "en": "3.8 Checking the start-up relief"
            },
            "type": "H3"
          }
        },
        {
          "id": "disclaimerValveStartRelief",
          "type": "htmlDisplay",
          "config": {
            "text": {
              "de": "Die Schließzeit der Anfahrentlastung wird gemessen, wobei diese über dem Staudruck (1/3 des Betriebsdruckes) eingestellt sein sollte.",
              "en": "The closing time of the start-up relief is measured and it should be set above the back pressure (1/3 of the operating pressure)."
            },
            "pdfHide": true
          }
        },
        {
          "id": "closingTime",
          "type": "singleLineTextInput",
          "config": {
            "label": {
              "text": {
                "de": "Schließzeit ts = (sek)",
                "en": "Closing Time = (sec)"
              }
            },
            "pdfWidth": 0.5
          }
        },
        {
          "id": "conditionStartUpRelief",
          "type": "staticSingleSelect",
          "config": {
            "label": {
              "text": {
                "de": "Funktion der Anfahrentlastung",
                "en": "Functionality of Start-up Relief"
              }
            },
            "value": {
              "options": {
                "good": {
                  "de": "Gut",
                  "en": "Good"
                },
                "bad": {
                  "de": "Schlecht",
                  "en": "Bad"
                }
              }
            },
            "pdfWidth": 0.5
          }
        },
        {
          "id": "causeBadFunctionality1",
          "type": "multiLineTextInput",
          "config": {
            "label": {
              "text": {
                "de": "wenn schlecht, Ursache",
                "en": "in case of bad functionality, give cause"
              }
            },
            "pdfWidth": 0.5,
            "pdfHideIfValueIsEmpty": true
          }
        },
        {
          "id": "line12",
          "type": "htmlDisplay",
          "config": {
            "text": {
              "de": "<hr>",
              "en": "<hr>"
            },
            "uiHide": true
          }
        },
        {
          "id": "headlineValveStartRelief",
          "type": "headlineDisplay",
          "config": {
            "text": {
              "de": "3.8.1 Magnetventil der Anfahrentlastung",
              "en": "3.8.1 Solenoid valve of the start-up relief"
            },
            "type": "H3"
          }
        },
        {
          "id": "headlineStartRelief2",
          "type": "htmlDisplay",
          "config": {
            "text": {
              "de": "Die Funktionstüchtigkeit des Magnetventis muss gewährleistet sein.",
              "en": "The functionality of the solenoid valve must be guaranteed."
            },
            "pdfHide": true
          }
        },
        {
          "id": "functionalitySolenoidValve",
          "type": "staticSingleSelect",
          "config": {
            "label": {
              "text": {
                "de": "Funktion des Mangnetventils",
                "en": "Functionality of solenoid valve"
              }
            },
            "value": {
              "options": {
                "yes": {
                  "de": "Ja",
                  "en": "Yes"
                },
                "no": {
                  "de": "Nein",
                  "en": "No"
                }
              }
            },
            "pdfWidth": 0.5
          }
        },
        {
          "id": "causeBadFunctionality2",
          "type": "multiLineTextInput",
          "config": {
            "label": {
              "text": {
                "de": "wenn schlecht, Ursache",
                "en": "in case of bad functionality, give cause"
              }
            },
            "pdfWidth": 0.5,
            "pdfHideIfValueIsEmpty": true
          }
        },
        {
          "id": "line13",
          "type": "htmlDisplay",
          "config": {
            "text": {
              "de": "<hr>",
              "en": "<hr>"
            },
            "uiHide": true
          }
        },
        {
          "id": "headlineCompensator",
          "type": "headlineDisplay",
          "config": {
            "text": {
              "de": "3.9 Überprüfung des Kompensators",
              "en": "3.9 Checking the compensator"
            },
            "type": "H3"
          }
        },
        {
          "id": "headlineCompensator2",
          "type": "htmlDisplay",
          "config": {
            "text": {
              "de": "Der Kompensator dient als elastische Verbindung zwischen Gebläseaggregat und Duckrohrleitung und muss daher spannungsfrei eingebaut sein.",
              "en": "The compensator serves as an elastic connection between the blower unit and the ducting pipe, and must therefore be installed stress-free."
            },
            "pdfHide": true
          }
        },
        {
          "id": "headlineCompensator3",
          "type": "htmlDisplay",
          "config": {
            "text": {
              "de": "Die Dichtigkeit des Kompensators ist Grunvoraussetzung für einen wirtschaftlichen Betrieb.",
              "en": "The tightness of the compensator is a basic requirement for economical operation."
            },
            "pdfHide": true
          }
        },
        {
          "id": "positionCompensator",
          "type": "staticSingleSelect",
          "config": {
            "label": {
              "text": {
                "de": "Einbaulage des Kompensators",
                "en": "Installation position of the compensator"
              }
            },
            "value": {
              "options": {
                "entlastet": {
                  "de": "Entlastet",
                  "en": "Stress-free"
                },
                "verspannt": {
                  "de": "Verspannt",
                  "en": "Under tension"
                }
              }
            },
            "pdfWidth": 0.5
          }
        },
        {
          "id": "tightnessCompensator",
          "type": "staticSingleSelect",
          "config": {
            "label": {
              "text": {
                "de": "Dichtigkeit",
                "en": "Tightness"
              }
            },
            "value": {
              "options": {
                "yes": {
                  "de": "Ja",
                  "en": "Yes"
                },
                "no": {
                  "de": "Nein",
                  "en": "No"
                }
              }
            },
            "pdfWidth": 0.5
          }
        },
        {
          "id": "causeLeakage",
          "type": "multiLineTextInput",
          "config": {
            "label": {
              "text": {
                "de": "wenn undicht, Ursache",
                "en": "in case of leakage, give cause"
              }
            },
            "pdfWidth": 0.5,
            "pdfHideIfValueIsEmpty": true
          }
        },
        {
          "id": "line14",
          "type": "htmlDisplay",
          "config": {
            "text": {
              "de": "<hr>",
              "en": "<hr>"
            },
            "uiHide": true
          }
        },
        {
          "id": "headlineInstrumentation",
          "type": "headlineDisplay",
          "config": {
            "text": {
              "de": "3.10 Funktion der Instrumentierung",
              "en": "3.10 Function of the instrumentation"
            },
            "type": "H3"
          }
        },
        {
          "id": "headlineInstrumentation2",
          "type": "headlineDisplay",
          "config": {
            "text": {
              "de": "3.10.1 Manometer",
              "en": "3.10.1 Manometer"
            },
            "type": "H3"
          }
        },
        {
          "id": "functionalityManometer",
          "type": "staticSingleSelect",
          "config": {
            "label": {
              "text": {
                "de": "Funktionstüchtigkeit",
                "en": "Functionality"
              }
            },
            "value": {
              "options": {
                "yes": {
                  "de": "Ja",
                  "en": "Yes"
                },
                "no": {
                  "de": "Nein",
                  "en": "No"
                }
              }
            },
            "pdfWidth": 0.5
          }
        },
        {
          "id": "causeBadFunctionality3",
          "type": "multiLineTextInput",
          "config": {
            "label": {
              "text": {
                "de": "wenn nicht, Ursache",
                "en": "in case of no functionality, give cause"
              }
            },
            "pdfWidth": 0.5,
            "pdfHideIfValueIsEmpty": true
          }
        },
        {
          "id": "line15",
          "type": "htmlDisplay",
          "config": {
            "text": {
              "de": "<hr>",
              "en": "<hr>"
            },
            "uiHide": true
          }
        },
        {
          "id": "headlineInstrumentation3",
          "type": "headlineDisplay",
          "config": {
            "text": {
              "de": "3.10.2 Wartungsanzeiger",
              "en": "3.10.2 Maintenance indicator"
            },
            "type": "H3"
          }
        },
        {
          "id": "functionalityMaintenanceIndicator",
          "type": "staticSingleSelect",
          "config": {
            "label": {
              "text": {
                "de": "Funktionstüchtigkeit",
                "en": "Functionality"
              }
            },
            "value": {
              "options": {
                "yes": {
                  "de": "Ja",
                  "en": "Yes"
                },
                "no": {
                  "de": "Nein",
                  "en": "No"
                }
              }
            },
            "pdfWidth": 0.5
          }
        },
        {
          "id": "causeBadFunctionality4",
          "type": "multiLineTextInput",
          "config": {
            "label": {
              "text": {
                "de": "wenn nicht, Ursache",
                "en": "in case of no functionality, give cause"
              }
            },
            "pdfWidth": 0.5,
            "pdfHideIfValueIsEmpty": true
          }
        },
        {
          "id": "line16",
          "type": "htmlDisplay",
          "config": {
            "text": {
              "de": "<hr>",
              "en": "<hr>"
            },
            "uiHide": true
          }
        },
        {
          "id": "headlineMachineFeet",
          "type": "headlineDisplay",
          "config": {
            "text": {
              "de": "3.11 Schwingungsisolationsprüfung der elastischen Maschinenfüße",
              "en": "3.11 Vibration isolation test of the elastic machine feet"
            },
            "type": "H3"
          }
        },
        {
          "id": "conditionMachineFeet",
          "type": "staticSingleSelect",
          "config": {
            "label": {
              "text": {
                "de": "Zustand Maschinenfüße",
                "en": "Condition machine feet"
              }
            },
            "value": {
              "options": {
                "good": {
                  "de": "Gut",
                  "en": "Good"
                },
                "bad": {
                  "de": "Schlecht",
                  "en": "Bad"
                }
              }
            },
            "pdfWidth": 0.5
          }
        },
        {
          "id": "causeBadCondition",
          "type": "multiLineTextInput",
          "config": {
            "label": {
              "text": {
                "de": "wenn schlecht, Ursache",
                "en": "in case of bad condition, give cause"
              }
            },
            "pdfWidth": 0.5,
            "pdfHideIfValueIsEmpty": true
          }
        },
        {
          "id": "line17",
          "type": "htmlDisplay",
          "config": {
            "text": {
              "de": "<hr>",
              "en": "<hr>"
            },
            "uiHide": true
          }
        },
        {
          "id": "headlineSoundHoodForcedVentilation",
          "type": "headlineDisplay",
          "config": {
            "text": {
              "de": "3.12 Funktion der Schallhaubenfremdbelüftung",
              "en": "3.12 Functionality of sound hood forced ventilation"
            },
            "type": "H3"
          }
        },
        {
          "id": "headlineSoundHoodForcedVentilation2",
          "type": "htmlDisplay",
          "config": {
            "text": {
              "de": "Die Zuluft- und Abluftkulissen der Schallhaube werden auf Verschmutzungen geprüft, damit der Schallhaubenlüfter keiner unzulässigen hohen Druckdifferenz ausgesetzt ist.",
              "en": "The intake and exhaust louvers of the sound hood are checked for dirt to ensure that the sound hood fan is not exposed to an excessive pressure difference."
            },
            "pdfHide": true
          }
        },
        {
          "id": "functionalityVentilator",
          "type": "staticSingleSelect",
          "config": {
            "label": {
              "text": {
                "de": "Funktion des Lüfters",
                "en": "Functionality of the ventilator"
              }
            },
            "value": {
              "options": {
                "good": {
                  "de": "Gut",
                  "en": "Good"
                },
                "bad": {
                  "de": "Schlecht",
                  "en": "Bad"
                }
              }
            },
            "pdfWidth": 0.5
          }
        },
        {
          "id": "causeBadFunctionality5",
          "type": "multiLineTextInput",
          "config": {
            "label": {
              "text": {
                "de": "wenn schlecht, Ursache",
                "en": "in case of bad functionality, give cause"
              }
            },
            "pdfWidth": 0.5,
            "pdfHideIfValueIsEmpty": true
          }
        },
        {
          "id": "line18",
          "type": "htmlDisplay",
          "config": {
            "text": {
              "de": "<hr>",
              "en": "<hr>"
            },
            "uiHide": true
          }
        },
        {
          "id": "headlineDriveMotor",
          "type": "headlineDisplay",
          "config": {
            "text": {
              "de": "3.13 Inspektion des Antriebmotors",
              "en": "3.13 Inspection of the drive motor"
            },
            "type": "H3"
          }
        },
        {
          "id": "headlineDriveMotor2",
          "type": "htmlDisplay",
          "config": {
            "text": {
              "de": "Die Laufruhe des Antriebsmotors wird beobachtet. Die Nachschmiereinrichtung und der Motorlüfter des Antriebmotors müssen funktionstüchtig sein.",
              "en": "The running smoothness of the drive motor is observed. The lubrication device and the motor fan of the drive motor must be functional."
            },
            "pdfHide": true
          }
        },
        {
          "id": "laufruhe2",
          "type": "staticSingleSelect",
          "config": {
            "label": {
              "text": {
                "de": "Laufruhe",
                "en": "Smoothness"
              }
            },
            "value": {
              "options": {
                "good": {
                  "de": "Gut",
                  "en": "Good"
                },
                "bad": {
                  "de": "Schlecht",
                  "en": "Bad"
                }
              }
            },
            "pdfWidth": 0.5
          }
        },
        {
          "id": "causeSmoothness",
          "type": "multiLineTextInput",
          "config": {
            "label": {
              "text": {
                "de": "wenn schlecht, evtl. Ursache",
                "en": "in case of bad smoothness, give cause"
              }
            },
            "pdfWidth": 0.5,
            "pdfHideIfValueIsEmpty": true
          }
        },
        {
          "id": "functionalityLubrication",
          "type": "staticSingleSelect",
          "config": {
            "label": {
              "text": {
                "de": "Funktion der Nachschmiereinrichtung",
                "en": "Functionality of the lubrication device"
              }
            },
            "value": {
              "options": {
                "good": {
                  "de": "Gut",
                  "en": "Good"
                },
                "bad": {
                  "de": "Schlecht",
                  "en": "Bad"
                }
              }
            },
            "pdfWidth": 0.5
          }
        },
        {
          "id": "causeSmoothness3",
          "type": "multiLineTextInput",
          "config": {
            "label": {
              "text": {
                "de": "wenn schlecht, evtl. Ursache",
                "en": "in case of bad smoothness, give cause"
              }
            },
            "pdfWidth": 0.5,
            "pdfHideIfValueIsEmpty": true
          }
        },
        {
          "id": "fatChange",
          "type": "staticSingleSelect",
          "config": {
            "label": {
              "text": {
                "de": "Fett muss gewechselt werden",
                "en": "Fat needs to be changed"
              }
            },
            "value": {
              "options": {
                "yes": {
                  "de": "Ja",
                  "en": "Yes"
                },
                "no": {
                  "de": "Nein",
                  "en": "No"
                }
              }
            },
            "pdfWidth": 0.5
          }
        },
        {
          "id": "coditionEngineFan",
          "type": "staticSingleSelect",
          "config": {
            "label": {
              "text": {
                "de": "Zustand des Motorlüfters",
                "en": "Condition of the engine fan"
              }
            },
            "value": {
              "options": {
                "good": {
                  "de": "Gut",
                  "en": "Good"
                },
                "bad": {
                  "de": "Schlecht",
                  "en": "Bad"
                }
              }
            },
            "pdfWidth": 0.5
          }
        },
        {
          "id": "causeBadConditionEngineFan",
          "type": "multiLineTextInput",
          "config": {
            "label": {
              "text": {
                "de": "wenn schlecht, evtl. Ursache",
                "en": "in case of bad condition, give cause"
              }
            },
            "pdfWidth": 0.5,
            "pdfHideIfValueIsEmpty": true
          }
        }
      ]
    },
    {
      "id": "05_furtherComments",
      "type": "fieldSection",
      "config": {
        "headline": {
          "text": {
            "de": "4. Kommentar zu den Mängeln",
            "en": "4. Comments regardig the defects"
          },
          "pdfHide": true
        }
      },
      "fields": [
        {
          "id": "whitespace4",
          "type": "headlineDisplay",
          "config": {
            "text": {
              "de": "",
              "en": ""
            },
            "uiHide": true,
            "pdfTextSize": "H2"
          }
        },
        {
          "id": "line19",
          "type": "htmlDisplay",
          "config": {
            "text": {
              "de": "<hr>",
              "en": "<hr>"
            },
            "uiHide": true
          }
        },
        {
          "id": "pdfHeadline18",
          "type": "headlineDisplay",
          "config": {
            "text": {
              "de": "4. Kommentar zu den Mängeln",
              "en": "4. Comments regardig the defects"
            },
            "pdfTextSize": "H2",
            "uiHide": true
          }
        },
        {
          "id": "furtherComments",
          "type": "multiLineTextInput",
          "config": {
            "label": {
              "text": {
                "de": "Kommentare",
                "en": "Commments"
              }
            }
          }
        }
      ]
    },
    {
      "id": "06_furtherMeasures",
      "type": "fieldSection",
      "config": {
        "headline": {
          "text": {
            "de": "5. Sofort durchzuführende Maßnahmen",
            "en": "5. Actions to be taken immediately"
          },
          "pdfHide": true
        }
      },
      "fields": [
        {
          "id": "whitespace5",
          "type": "headlineDisplay",
          "config": {
            "text": {
              "de": "",
              "en": ""
            },
            "uiHide": true,
            "pdfTextSize": "H2"
          }
        },
        {
          "id": "line20",
          "type": "htmlDisplay",
          "config": {
            "text": {
              "de": "<hr>",
              "en": "<hr>"
            },
            "uiHide": true
          }
        },
        {
          "id": "pdfHeadline19",
          "type": "headlineDisplay",
          "config": {
            "text": {
              "de": "5. Sofort durchzuführende Maßnahmen",
              "en": "5. Actions to be taken immediately"
            },
            "pdfTextSize": "H2",
            "uiHide": true
          }
        },
        {
          "id": "headlineFurtherMeasures",
          "type": "htmlDisplay",
          "config": {
            "text": {
              "de": "Sofort durchzuführende Reparaturen müssen vom Kunden genehmigt und nachstehend beauftragt werden. (Zeitpunkt ist auf einem gesonderten Stundenzettel aufzuführen und vom Auftraggeber zu paragraphieren.)",
              "en": "Immediate repairs must be approved by the customer and commissioned below. (The time is to be recorded on a separate hourly sheet and itemized by the client.)"
            },
            "pdfHide": true
          }
        },
        {
          "id": "furtherMeasures",
          "type": "multiLineTextInput",
          "config": {
            "label": {
              "text": {
                "de": "Liste sofort durchzuführender Maßnahmen",
                "en": "List of immediately to be taken actions"
              }
            }
          }
        },
        {
          "id": "technicianFurtherMeasures",
          "type": "userSingleSelect",
          "config": {
            "label": {
              "text": {
                "de": "Verantwortlicher Monteur",
                "en": "Responsible Technician"
              }
            },
            "prefill": {
              "value": [
                {
                  "input": "currentUserId",
                  "steps": []
                }
              ]
            }
          }
        }
      ]
    },
    {
      "id": "08_spareParts",
      "type": "fieldSection",
      "config": {
        "headline": {
          "text": {
            "de": "6. Benötigte Ersatzteile",
            "en": "6. Required spare parts"
          },
          "pdfHide": true
        }
      },
      "fields": [
        {
          "id": "whitespace6",
          "type": "headlineDisplay",
          "config": {
            "text": {
              "de": "",
              "en": ""
            },
            "uiHide": true,
            "pdfTextSize": "H2"
          }
        },
        {
          "id": "pdfHeadline20",
          "type": "headlineDisplay",
          "config": {
            "text": {
              "de": "6. Benötigte Ersatzteile",
              "en": "6. Required spare parts"
            },
            "pdfTextSize": "H2",
            "uiHide": true
          }
        },
        {
          "id": "spareParts",
          "type": "partListInput",
          "config": {
            "label": {
              "text": {
                "de": "Ersatzteile",
                "en": "Spare parts"
              }
            },
            "fields": {
              "partNumberSingleLineTextInput": {
                "required": true,
                "pdfHide": false,
                "placeHolderText": {
                  "de": "Bezeichnung",
                  "en": "Name"
                }
              },
              "quantityNumericInput": {
                "required": true,
                "pdfHide": false
              },
              "descriptionMultiLineTextInput": {
                "enable": true,
                "required": false,
                "pdfHide": false,
                "placeHolderText": {
                  "de": "Beschreibung/Bemerkung",
                  "en": "Description/Comment"
                }
              }
            }
          }
        }
      ]
    },
    {
      "id": "09_otherAgreements",
      "type": "fieldSection",
      "config": {
        "headline": {
          "text": {
            "de": "7. Sonstige Vereinbarungen",
            "en": "7. Other Agreements"
          },
          "pdfHide": true
        }
      },
      "fields": [
        {
          "id": "whitespace7",
          "type": "headlineDisplay",
          "config": {
            "text": {
              "de": "",
              "en": ""
            },
            "uiHide": true,
            "pdfTextSize": "H2"
          }
        },
        {
          "id": "pdfHeadline21",
          "type": "headlineDisplay",
          "config": {
            "text": {
              "de": "7. Sonstige Vereinbarungen",
              "en": "7. Other Agreements"
            },
            "uiHide": true,
            "pdfTextSize": "H2"
          }
        },
        {
          "id": "nextInspection",
          "type": "singleLineTextInput",
          "config": {
            "label": {
              "text": {
                "de": "Nächster Inspektionstermin",
                "en": "Next Inspection"
              }
            },
            "pdfWidth": 0.5
          }
        },
        {
          "id": "maintenanceAppointment",
          "type": "singleLineTextInput",
          "config": {
            "label": {
              "text": {
                "de": "Evtl. erforderlicher Wartungstermin",
                "en": "Possibly required maintenance date"
              }
            },
            "pdfWidth": 0.5,
            "pdfHideIfValueIsEmpty": true
          }
        }
      ]
    },
    {
      "id": "10_signatureTechnician",
      "type": "signatureSection",
      "config": {
        "headlineText": {
          "de": "Unterschrift Monteuer",
          "en": "Signature Technician"
        },
        "required": true,
        "hideDownloadPdfButton": false,
        "hidePreviewPdfButton": false,
        "pdfHideIfValueIsEmpty": true,
        "pdfHide": false,
        "helpTextHtmlBelow": {
          "text": {
            "de": "Die Inspektion wurde fachgerecht durchgeführt.",
            "en": "Maintenance was professionally performed."
          },
          "pdfHide": true
        },
        "fields": {
          "dateInput": {
            "required": true,
            "pdfHide": false,
            "disable": false,
            "autofill": "always"
          },
          "locationSingleLineTextInput": {
            "required": true,
            "pdfHide": false,
            "disable": false
          },
          "nameSingleLineTextInput": {
            "required": true,
            "pdfHide": false,
            "disable": false,
            "capitalizeFirstLetterOfEveryWord": true
          }
        },
        "prefill": {
          "name": [
            {
              "input": "assignedUserId",
              "steps": [
                "userIdToUser",
                "userToFullNameString"
              ]
            }
          ],
          "location": [
            {
              "input": "assetId",
              "steps": [
                "assetIdToAsset",
                "assetToLocationAddress",
                "addressToCityString"
              ]
            }
          ]
        }
      }
    },
    {
      "id": "11_send",
      "type": "emailSection",
      "config": {
        "headlineText": {
          "de": "Bericht als E-Mail senden/gesendet",
          "en": "Send/sent report as email"
        },
        "pdfHide": true,
        "hideDownloadPdfButton": false,
        "hidePreviewPdfButton": false,
        "emailDialogPrefill": {
          "subject": {
            "de": "Wartungsbericht Drehkolbengebläse",
            "en": "Maintenance Report Roots Blower"
          },
          "body": {
            "de": "Diese E-Mail wurde automatisch generiert.\nBitte antworten Sie nicht auf diese E-Mail.\n\nSehr geehrte Damen und Herren,\n\nim Anhang finden Sie den abgeschlossenen Wartungsbericht als PDF.\n\nMit freundlichen Grüßen",
            "en": "This email was generated automatically.\nPlease do not reply to this email.\n\nDear Sir or Madam,\n\nIn the attachment you will find the completed maintenance report as PDF.\n\nBest regards"
          },
          "cc": {
            "staticEmails": [
              "t.marschner@wksgroup.de"
            ]
          }
        }
      }
    }
  ]
}
